mizan_embedder/__init__.py
mizan_embedder/data.py
mizan_embedder/model.py
mizan_embedder-0.3.1.dist-info/licenses/LICENSE
mizan_embedder-0.3.1.dist-info/METADATA
mizan_embedder-0.3.1.dist-info/WHEEL
mizan_embedder-0.3.1.dist-info/top_level.txt
mizan_embedder-0.3.1.dist-info/RECORD
