Metadata-Version: 2.4
Name: mizan-embedder
Version: 0.3.1
Summary: Mizan-optimized embedding model training
Author: Ahsan Shaokat
License: MIT
Requires-Python: >=3.9
License-File: LICENSE
Requires-Dist: torch
Requires-Dist: transformers
Requires-Dist: mizan-vector
Provides-Extra: dev
Requires-Dist: pytest; extra == "dev"
Requires-Dist: datasets; extra == "dev"
Dynamic: license-file
